{
  "id": 1,
  "name": "subcloud1",
  "created-at": "2023-01-02T03:04:05.678987",
  "updated-at": "2023-04-08T15:16:23.424851",
  "availability-status": "online",
  "data_install": null,
  "data_upgrade": null,
  "deploy-status": "complete",
  "backup-status": "complete",
  "backup-datetime": "2023-05-02 11:23:58.132134",
  "region-name": "bbadb3e8e2ab473792c80ef09c5a12a4",
  "description": "Ottawa Site",
  "group_id": 1,
  "location": "YOW",
  "management-end-ip": "192.168.101.50",
  "management-gateway-ip": "192.168.101.1",
  "management-start-ip": "192.168.101.2",
  "management-state": "unmanaged",
  "management-subnet": "192.168.101.0/24",
  "openstack-installed": false,
  "software-version": "21.12",
  "systemcontroller-gateway-ip": "192.168.204.101"
}